EnergyEfficientAI/EnergyConsumptionDL.py
EnergyEfficientAI/EnergyConsumptionML.py
EnergyEfficientAI/Message.py
EnergyEfficientAI/__init__.py
EnergyEfficientAI-0.7.dist-info/METADATA
EnergyEfficientAI-0.7.dist-info/WHEEL
EnergyEfficientAI-0.7.dist-info/top_level.txt
EnergyEfficientAI-0.7.dist-info/RECORD
