Metadata-Version: 2.1
Name: EnergyEfficientAI
Version: 0.7
Summary: A library to calculate Energy and Power consumption of machine learning and deep learning algorithms
Author: Uzair Hassan, Zia Ur Rehman, Saif Ul Islam
Classifier: Programming Language :: Python :: 3
Classifier: License :: OSI Approved :: MIT License
Classifier: Operating System :: OS Independent
Requires-Python: >=3.6
Requires-Dist: numpy
Requires-Dist: psutil
Requires-Dist: scikit-learn
Requires-Dist: seaborn
